flask_crlatency/__init__.py
flask_crlatency-0.0.2.dist-info/LICENSE
flask_crlatency-0.0.2.dist-info/METADATA
flask_crlatency-0.0.2.dist-info/WHEEL
flask_crlatency-0.0.2.dist-info/top_level.txt
flask_crlatency-0.0.2.dist-info/RECORD
