Metadata-Version: 2.1
Name: flask-crlatency
Version: 0.0.2
Summary: A flask extension to log route latency 
Home-page: https://github.com/Agent-Hellboy/flask-crlatency
Author: Prince Roshan
Author-email: princekrroshan01@gmail.com
License: MIT
Keywords: flask-extension,log-route-latency
Classifier: Programming Language :: Python :: 3.8
Classifier: Programming Language :: Python :: 3.9
Classifier: Programming Language :: Python :: 3.10
Classifier: Programming Language :: Python :: 3.11
Classifier: Operating System :: OS Independent
Requires-Python: >=3.8
License-File: LICENSE
